{
  "host": "localhost",
  "port": "27017",
  "db_name": "example",
  "collections": [
    {
      "name": "collection1",
      "documents": [
        {
          "foo": "bar",
          "john": "doe"
        }
      ]
    },
    {
      "name": "collection2",
      "documents": [
        {
          "title": "Never Gonna Give You Up",
          "artist": "Rick Astley",
          "album": "Whenever You Need Somebody",
          "genre": "Dance pop",
          "label": "RCA",
          "formats": [
            {
              "type": "Vinyl",
              "sizes": ["7 inches, 12 inches"]
            },
            {
              "type": "CD"
            }
          ]
        },
        {
          "title": "Changed My Mind",
          "artist": "Todrick Hall",
          "album": "Forbidden",
          "genre": "Pop",
          "label": "Self-released",
          "formats": [
            {
              "type": "Digital download"
            },
            {
              "type": "Streaming"
            }
          ]
        }
      ]
    }
  ]
}